pyhub_office_automation/__init__.py
pyhub_office_automation/version.py
pyhub_office_automation/cli/__init__.py
pyhub_office_automation/cli/main.py
pyhub_office_automation/excel/__init__.py
pyhub_office_automation/excel/chart_add.py
pyhub_office_automation/excel/chart_configure.py
pyhub_office_automation/excel/chart_delete.py
pyhub_office_automation/excel/chart_export.py
pyhub_office_automation/excel/chart_list.py
pyhub_office_automation/excel/chart_pivot_create.py
pyhub_office_automation/excel/chart_position.py
pyhub_office_automation/excel/pivot_configure.py
pyhub_office_automation/excel/pivot_create.py
pyhub_office_automation/excel/pivot_delete.py
pyhub_office_automation/excel/pivot_list.py
pyhub_office_automation/excel/pivot_refresh.py
pyhub_office_automation/excel/range_read.py
pyhub_office_automation/excel/range_write.py
pyhub_office_automation/excel/shape_add.py
pyhub_office_automation/excel/shape_delete.py
pyhub_office_automation/excel/shape_format.py
pyhub_office_automation/excel/shape_group.py
pyhub_office_automation/excel/shape_list.py
pyhub_office_automation/excel/sheet_activate.py
pyhub_office_automation/excel/sheet_add.py
pyhub_office_automation/excel/sheet_delete.py
pyhub_office_automation/excel/sheet_rename.py
pyhub_office_automation/excel/slicer_add.py
pyhub_office_automation/excel/slicer_connect.py
pyhub_office_automation/excel/slicer_list.py
pyhub_office_automation/excel/slicer_position.py
pyhub_office_automation/excel/table_read.py
pyhub_office_automation/excel/table_write.py
pyhub_office_automation/excel/textbox_add.py
pyhub_office_automation/excel/utils.py
pyhub_office_automation/excel/workbook_create.py
pyhub_office_automation/excel/workbook_info.py
pyhub_office_automation/excel/workbook_list.py
pyhub_office_automation/excel/workbook_open.py
pyhub_office_automation/hwp/__init__.py
pyhub_office_automation/utils/__init__.py
pyhub_office_automation/utils/resource_loader.py
tests/__init__.py
tests/conftest.py
tests/test_excel_create_workbook.py
pyhub_office_automation-5.2538.2.dist-info/METADATA
pyhub_office_automation-5.2538.2.dist-info/WHEEL
pyhub_office_automation-5.2538.2.dist-info/entry_points.txt
pyhub_office_automation-5.2538.2.dist-info/top_level.txt
pyhub_office_automation-5.2538.2.dist-info/RECORD
