Metadata-Version: 2.4
Name: pyhub-office-automation
Version: 5.2538.2
Summary: Python-based Excel and HWP automation package for AI agents
Home-page: https://github.com/pyhub-apps/pyhub-office-automation
Author: Chinseok Lee
Author-email: Chinseok Lee <me@pyhub.kr>
License: MIT
Project-URL: Homepage, https://github.com/pyhub-apps/pyhub-office-automation
Project-URL: Repository, https://github.com/pyhub-apps/pyhub-office-automation
Project-URL: Issues, https://github.com/pyhub-apps/pyhub-office-automation/issues
Keywords: office,automation,excel,hwp,ai,agent,cli
Platform: Windows
Classifier: Development Status :: 3 - Alpha
Classifier: Intended Audience :: End Users/Desktop
Classifier: License :: OSI Approved :: MIT License
Classifier: Operating System :: Microsoft :: Windows
Classifier: Programming Language :: Python :: 3
Classifier: Programming Language :: Python :: 3.13
Classifier: Topic :: Office/Business
Classifier: Topic :: Software Development :: Libraries :: Python Modules
Requires-Python: >=3.13
Requires-Dist: typer>=0.9.0
Requires-Dist: xlwings>=0.30.0
Requires-Dist: pyhwpx>=0.2.0; sys_platform == "win32"
Requires-Dist: pandas>=2.0.0
Requires-Dist: pathlib2>=2.3.0
Requires-Dist: typing-extensions>=4.0.0
Provides-Extra: dev
Requires-Dist: pytest>=7.0.0; extra == "dev"
Requires-Dist: pytest-cov>=4.0.0; extra == "dev"
Requires-Dist: pytest-mock>=3.10.0; extra == "dev"
Requires-Dist: black>=24.0.0; extra == "dev"
Requires-Dist: isort>=5.13.0; extra == "dev"
Requires-Dist: flake8>=7.0.0; extra == "dev"
Requires-Dist: pre-commit>=3.0.0; extra == "dev"
Provides-Extra: build
Requires-Dist: pyinstaller>=5.0.0; extra == "build"
Dynamic: author
Dynamic: home-page
Dynamic: platform
Dynamic: requires-python
